jobrunner_git/__init__.py
jobrunner_git/project.py
jobrunner_git-1.0.6.dist-info/METADATA
jobrunner_git-1.0.6.dist-info/WHEEL
jobrunner_git-1.0.6.dist-info/entry_points.txt
jobrunner_git-1.0.6.dist-info/RECORD
